historian/base/__init__.py
historian/base/base_historian.py
historian/testing/__init__.py
historian/testing/integration_test_interface.py
volttron_lib_base_historian-0.1.0.dist-info/LICENSE
volttron_lib_base_historian-0.1.0.dist-info/WHEEL
volttron_lib_base_historian-0.1.0.dist-info/METADATA
volttron_lib_base_historian-0.1.0.dist-info/RECORD
