Metadata-Version: 2.1
Name: volttron-lib-base-historian
Version: 0.1.0
Summary: A base library with extension points for using with the VOLTTRON platform.
Home-page: https://github.com/eclipse-volttron/volttron-lib-base-historian
License: Apache-2.0
Author: VOLTTRON Team
Author-email: volttron@pnnl.gov
Requires-Python: >=3.8,<4.0
Classifier: License :: OSI Approved :: Apache Software License
Classifier: Programming Language :: Python :: 3
Classifier: Programming Language :: Python :: 3.8
Classifier: Programming Language :: Python :: 3.9
Classifier: Programming Language :: Python :: 3.10
Classifier: Programming Language :: Python :: 3.11
Requires-Dist: ply (>=3.11,<4.0)
Requires-Dist: volttron (>=10.0.2rc0,<11.0)
Project-URL: Repository, https://github.com/eclipse-volttron/volttron-lib-base-historian
